jinja2_pai_custom_filters/__init__.py
jinja2_pai_custom_filters/filters.py
jinja2_pai_custom_filters-0.0.2.dist-info/AUTHORS.rst
jinja2_pai_custom_filters-0.0.2.dist-info/LICENSE.txt
jinja2_pai_custom_filters-0.0.2.dist-info/METADATA
jinja2_pai_custom_filters-0.0.2.dist-info/WHEEL
jinja2_pai_custom_filters-0.0.2.dist-info/top_level.txt
jinja2_pai_custom_filters-0.0.2.dist-info/RECORD
